LICENSE
MANIFEST.in
README.rst
setup.py
eastdetector/__init__.py
eastdetector.egg-info/PKG-INFO
eastdetector.egg-info/SOURCES.txt
eastdetector.egg-info/dependency_links.txt
eastdetector.egg-info/requires.txt
eastdetector.egg-info/top_level.txt
eastdetector/model/__init__.py
eastdetector/model/resnet_utils.py
eastdetector/model/resnet_v1.py