Metadata-Version: 1.1
Name: eastdetector
Version: 1.0.3
Summary: EAST text detector
Home-page: https://github.com/Parquery/east-detector
Author: argmen (boostczc@gmail.com) is code author, Dominik Walder (dominik.walder@parquery.com) and Marko Ristin (marko@parquery.com) only packaged and wrapped the code
Author-email: devs@parquery.com
License: GNU General Public License v3.0
Keywords: east text detector
Platform: UNKNOWN
Classifier: Development Status :: 5 - Production/Stable
Classifier: Intended Audience :: Developers
Classifier: Topic :: Scientific/Engineering :: Artificial Intelligence
Classifier: License :: OSI Approved :: GNU General Public License v3 (GPLv3)
Classifier: Programming Language :: Python :: 3.5
